{
    "avg": {
        "wmc": 5.42,
        "ccn": 2.89,
        "bugs": 0.1,
        "kanDefect": 0.31,
        "relativeSystemComplexity": 62.14,
        "relativeDataComplexity": 1.77,
        "relativeStructuralComplexity": 60.37,
        "volume": 306.98,
        "commentWeight": 31.81,
        "intelligentContent": 82.67,
        "lcom": 1.42,
        "instability": 0.67,
        "afferentCoupling": 0.74,
        "efferentCoupling": 2.63,
        "difficulty": 5.19,
        "mi": 89.41,
        "distance": 0.34,
        "incomingCDep": 2,
        "incomingPDep": 0.8,
        "outgoingCDep": 3.8,
        "outgoingPDep": 2.6,
        "classesPerPackage": 3.8
    },
    "sum": {
        "loc": 966,
        "cloc": 259,
        "lloc": 709,
        "nbMethods": 67,
        "nbClasses": 19,
        "nbInterfaces": 0,
        "nbPackages": 5,
        "violations": {
            "total": 2,
            "information": 0,
            "warning": 2,
            "error": 0,
            "critical": 0
        }
    }
}